{
  "id": "lorex-lne9242b",
  "brand": "Lorex",
  "model": "Lorex 4K IP Wired Dome Security Camera with Listen-in Audio and Real-Time 30FPS Recording",
  "aliases": [
    "LNE9242B",
    "LNE9252B",
    "N3 Nocturnal Series"
  ],
  "type": "dome",
  "connectivity": [
    "ethernet"
  ],
  "resolution": {
    "megapixels": 8,
    "max_width": 3840,
    "max_height": 2160,
    "label": "4K"
  },
  "sensor": "1/2.8\" CMOS",
  "lens": {
    "count": 1
  },
  "field_of_view_deg": "107",
  "night_vision": {
    "type": "hybrid",
    "range_m": 46
  },
  "power": {
    "method": "PoE (802.3af Class) / 12V DC"
  },
  "storage": {
    "onboard": true,
    "nvr_compatible": false,
    "cloud": false,
    "notes": "microSD slot present; maximum capacity not confirmed on the official page."
  },
  "protocols": [],
  "ip_rating": "IP67",
  "audio": {
    "microphone": true,
    "speaker": false,
    "two_way": false
  },
  "weight_g": 480,
  "operating_temp_c": "-40 to 60",
  "environment": [
    "outdoor"
  ],
  "features": [
    "listen-in audio (microphone only, no speaker/two-way talk confirmed)",
    "real-time 30fps recording, HDR",
    "aluminum housing",
    "color + IR night vision",
    "no officially confirmed RTSP/ONVIF -- not listed on the official product page"
  ],
  "sources": [
    "https://www.lorex.com/products/4k-8mp-smart-ip-dome-security-camera-with-listen-in-audio-and-real-time-30fps-recording"
  ],
  "power_source": [
    "poe",
    "dc"
  ],
  "last_verified": "2026-07-06"
}
