{
  "id": "abus-hdcc35512",
  "brand": "ABUS",
  "model": "HDCC35512",
  "type": "bullet",
  "connectivity": [
    "coax"
  ],
  "power_source": [
    "dc"
  ],
  "resolution": {
    "label": "5MP",
    "max_width": 2960,
    "max_height": 1665,
    "megapixels": 5
  },
  "video": {
    "max_fps": 20,
    "streams": [
      {
        "name": "main",
        "resolution": "2960x1665",
        "fps": 20
      }
    ]
  },
  "sensor": "1/2.8\" Progressive Scan CMOS",
  "lens": {
    "count": 1,
    "focal_length_mm": "2.8",
    "aperture": "F1.0",
    "varifocal": false
  },
  "field_of_view_deg": "112 horizontal, 60 vertical",
  "night_vision": {
    "type": "hybrid",
    "range_m": 30
  },
  "power": {
    "method": "12 V DC (+/-25%)"
  },
  "protocols": [],
  "ip_rating": "IP67",
  "audio": {
    "microphone": true,
    "speaker": false,
    "two_way": false
  },
  "features": [
    "True WDR (130 dB)",
    "Day/Night with electromechanical IR cut filter",
    "Color night vision (white-light LEDs)",
    "AI person/vehicle detection with HDCC900X2 recorder",
    "Switchable HD-TVI/AHD/HD-CVI/CVBS output",
    "Integrated microphone",
    "Up to 7.2 W power consumption"
  ],
  "operating_temp_c": "-30 to 60",
  "dimensions_mm": "172 x 69 x 69",
  "weight_g": 432,
  "environment": [
    "indoor",
    "outdoor"
  ],
  "sources": [
    "https://www.expert-security.de/abus-hdcc35512-analog-hd-mini-tube-5mpx-tn-ir-ip67.html",
    "https://alarm-technik.eu/en/products/abus-analog-hd-mini-tube-5-mpx-2-8-mm-hdcc35512"
  ],
  "last_verified": "2026-07-05"
}
