{
  "id": "hanwha-pnd-a9081rv",
  "brand": "Hanwha",
  "model": "PND-A9081RV",
  "markets": [
    "global"
  ],
  "aliases": [
    "Wisenet P 4K AI IR Indoor Vandal Dome"
  ],
  "type": "dome",
  "connectivity": [
    "ethernet"
  ],
  "resolution": {
    "megapixels": 8,
    "max_width": 3840,
    "max_height": 2160,
    "label": "4K UHD"
  },
  "sensor": "1/1.8\" CMOS",
  "lens": {
    "count": 1,
    "focal_length_mm": "4.5-10 (2.2x motorized varifocal)",
    "aperture": "F1.6-2.65",
    "varifocal": true
  },
  "field_of_view_deg": "101.4-45.5 horizontal / 53.6-25.5 vertical",
  "night_vision": {
    "type": "ir",
    "range_m": 30
  },
  "power": {
    "method": "PoE+ (IEEE 802.3at) / 12VDC",
    "consumption_w": 20,
    "voltage": "12VDC"
  },
  "power_source": [
    "poe",
    "dc"
  ],
  "storage": {
    "onboard": true,
    "max_microsd_gb": 512,
    "nvr_compatible": true,
    "cloud": false,
    "notes": "2 microSD/SDHC/SDXC slots (512GB total)."
  },
  "protocols": [
    "onvif",
    "rtsp",
    "http"
  ],
  "ip_rating": "IP52",
  "audio": {
    "microphone": true,
    "speaker": false,
    "two_way": false
  },
  "features": [
    "4K AI IR indoor vandal dome (Wisenet P AI series)",
    "AI object detection: person / face / vehicle / license plate + BestShot",
    "WiseIR 30m",
    "120 dB WDR",
    "IK10",
    "WiseStream II / WiseStream III (AI engine)",
    "built-in microphone (selectable mic/line in) + line out",
    "P-iris motorized varifocal",
    "ONVIF Profile S/G/T/M",
    "NDAA compliant"
  ],
  "release_year": 2020,
  "release_notes": "Corrected 2026-07-04: previous entry had a fabricated 3.9-9mm F1.4 lens; the real PND-A9081RV uses the same 4.5-10mm F1.6-2.65 optics as its PNO/PNV-A9081R siblings.",
  "sources": [
    "https://www.hanwhavision.com/en/products/camera/network/dome/pnd-a9081rv/"
  ],
  "last_verified": "2026-07-04",
  "configs": {
    "frigate": {
      "detect": {
        "width": 1280,
        "height": 720,
        "fps": 5
      },
      "rtsp_url_template": "rtsp://{user}:{pass}@{ip}:554/profile1/media.smp",
      "best_substream": "rtsp://{user}:{pass}@{ip}:554/profile2/media.smp"
    },
    "home_assistant": {
      "integration": "onvif",
      "notes": "Use ONVIF integration. Default ONVIF port 80."
    },
    "blue_iris": {
      "profile": "Samsung/Hanwha",
      "notes": "Select 'Samsung' or 'Hanwha' profile depending on Blue Iris version."
    }
  },
  "dimensions_mm": "Ø160 x 125",
  "weight_g": 1600,
  "operating_temp_c": "-25 to 50",
  "video": {
    "codecs": [
      "H.265",
      "H.264",
      "MJPEG"
    ],
    "max_fps": 30,
    "streams": [
      {
        "name": "main",
        "resolution": "3840x2160",
        "fps": 30,
        "codec": "H.265"
      }
    ]
  },
  "environment": [
    "indoor"
  ]
}
