{
  "id": "bosch-mic-7522-z30w",
  "brand": "Bosch",
  "model": "MIC IP starlight 7100i (MIC-7522-Z30W)",
  "type": "ptz",
  "connectivity": [
    "ethernet"
  ],
  "power_source": [
    "poe",
    "ac-mains"
  ],
  "resolution": {
    "label": "1080p HD",
    "max_width": 1920,
    "max_height": 1080,
    "megapixels": 2.12
  },
  "video": {
    "codecs": [
      "H.265",
      "H.264",
      "M-JPEG",
      "JPEG"
    ],
    "max_fps": 60,
    "streams": [
      {
        "name": "Stream 1 (configurable)",
        "codec": "H.265",
        "resolution": "1920x1080",
        "fps": 60
      },
      {
        "name": "Stream 2 (configurable)",
        "codec": "H.264",
        "resolution": "1920x1080",
        "fps": 60
      }
    ]
  },
  "sensor": "1/2 in. CMOS",
  "lens": {
    "count": 1,
    "varifocal": true,
    "focal_length_mm": "6.6-198",
    "aperture": "F1.5-F4.8"
  },
  "field_of_view_deg": "2.1-58.3",
  "night_vision": {
    "type": "color"
  },
  "power": {
    "method": "High Power-over-Ethernet (56 VDC nominal) or 24 VAC"
  },
  "storage": {
    "onboard": false,
    "nvr_compatible": true
  },
  "protocols": [
    "onvif",
    "rtsp",
    "http"
  ],
  "ip_rating": "IP68",
  "audio": {
    "two_way": true
  },
  "features": [
    "Starlight low-light technology (color 0.0047 lx, mono 0.0013 lx)",
    "120 dB High Dynamic Range (HDR/WDR)",
    "30x optical zoom + 12x digital zoom",
    "360 degree continuous pan, 290 degree tilt",
    "Intelligent Video Analytics on the edge",
    "Intelligent Tracking",
    "Camera Trainer (machine learning object detection)",
    "Image stabilization",
    "IK10 impact resistance, Type 6P",
    "Integrated window wiper",
    "ONVIF Profile S/G/T/M",
    "TPM / Embedded Login Firewall data security",
    "256 pre-positions",
    "Optional multispectral IR/white-light illuminator (up to 550 m)",
    "Quad streaming",
    "Two-way full-duplex audio (line in/out)"
  ],
  "operating_temp_c": "-40 to +65",
  "dimensions_mm": "287.93 x 400.34 x 210.65",
  "weight_g": 8700,
  "environment": [
    "outdoor"
  ],
  "sources": [
    "https://www.a1securitycameras.com/content/product_documents/53017/Bosch-MIC-7522-Z30W-Datasheet-A1.pdf",
    "https://files.eetgroup.com/Bosch/Datasheets/MIC_IP_starlight_7100i_Datasheet_51_en_68540570251%20final%20(003).pdf",
    "https://commerce.boschsecurity.com/id/en/MIC-IP-starlight-7100i/p/F.01U.353.589/",
    "https://netcamcenter.de/de/produkte/ip-kameras/mic-7522-z30w"
  ],
  "markets": [
    "EU",
    "global"
  ],
  "configs": {
    "frigate": {
      "detect": {
        "width": 1920,
        "height": 1080,
        "fps": 5
      },
      "rtsp_url_template": "rtsp://{user}:{pass}@{ip}:554/?inst=1",
      "best_substream": "rtsp://{user}:{pass}@{ip}:554/?inst=2",
      "recommended_stream_type": "go2rtc",
      "verified": false,
      "notes": "Bosch official RTSP scheme: /?inst=1 main, /?inst=2 sub (per Bosch 'RTSP usage with Bosch Video IP Devices'). Default admin user is 'service' (no factory default password — set one first). ONVIF Profile S/G (T/M on INTEOX). Not individually bench-tested."
    },
    "home_assistant": {
      "integration": "onvif",
      "connection_type": "local_push",
      "onvif_events": true,
      "notes": "Generic ONVIF integration; Bosch CPP cameras are ONVIF Profile S/G compliant. Use the 'service' account."
    },
    "blue_iris": {
      "profile": "ONVIF",
      "notes": "Bosch — use the ONVIF/RTSP (or 'Bosch') profile; default admin user is 'service'."
    }
  },
  "last_verified": "2026-07-06"
}
