{
  "id": "bosch-nde-8704-rl",
  "brand": "Bosch",
  "model": "FLEXIDOME 8100i IR (NDE-8704-RL)",
  "type": "dome",
  "connectivity": [
    "ethernet"
  ],
  "power_source": [
    "poe",
    "dc",
    "ac-mains"
  ],
  "resolution": {
    "label": "4K UHD",
    "max_width": 3840,
    "max_height": 2160,
    "megapixels": 8.3
  },
  "video": {
    "codecs": [
      "H.264",
      "H.265",
      "M-JPEG"
    ],
    "max_fps": 30,
    "streams": [
      {
        "name": "main",
        "resolution": "3840x2160",
        "codec": "H.265",
        "fps": 30
      },
      {
        "name": "HDR",
        "resolution": "3840x2160",
        "codec": "H.265",
        "fps": 20
      }
    ]
  },
  "sensor": "1/1.8\" CMOS, 2.0 μm",
  "lens": {
    "count": 1,
    "focal_length_mm": "3.9-10",
    "aperture": "F1.6-F2.7",
    "varifocal": true
  },
  "field_of_view_deg": "117°-62° horizontal, 44°-24° vertical",
  "night_vision": {
    "type": "ir",
    "range_m": 30
  },
  "power": {
    "method": "PoE+ (IEEE 802.3at Type 2, Class 4); 24 VAC; 12-26 VDC",
    "poe_class": 4
  },
  "storage": {
    "onboard": true,
    "max_microsd_gb": 2048,
    "cloud": true,
    "nvr_compatible": true
  },
  "protocols": [
    "onvif",
    "rtsp",
    "http"
  ],
  "ip_rating": "IP66/IP67/IP6K9K",
  "audio": {
    "microphone": true,
    "speaker": false,
    "two_way": true
  },
  "features": [
    "Starlight low-light technology",
    "120 dB HDR",
    "Remote PTRZ (pan-tilt-roll-zoom) commissioning",
    "IVA Pro Buildings / Perimeter / Privacy deep-learning analytics",
    "Electronic image stabilization (EIS)",
    "Dual microSD edge recording (mirror/failover/extend)",
    "P-iris motorized lens with autofocus",
    "Built-in microphone, audio line in/out (full duplex)",
    "850nm split IR illumination up to 30m",
    "Tamper detection",
    "8 privacy masks",
    "TPM crypto coprocessor, TLS 1.2/1.3, 802.1x",
    "NDAA compliant",
    "ONVIF Profile S/G/T/M",
    "IK11 vandal resistance",
    "CPP14 platform with neural processing engine"
  ],
  "operating_temp_c": "-50 to 60",
  "dimensions_mm": "175 x 148 (Ø x H)",
  "weight_g": 2300,
  "release_year": 2024,
  "environment": [
    "indoor",
    "outdoor"
  ],
  "sources": [
    "https://www.sveistrup.dk/files/data/doc/datasheets/Bosch/NDE-8704-RL.pdf",
    "https://commerce.keenfinity.tech/us/en/FLEXIDOME-8100i-IR/p/F.01U.411.099/",
    "https://netcamcenter.de/de/produkte/ip-kameras/nde-8704-rl",
    "https://madison.tech/products/bosch-flexidome-8100i-ir-nde-8704-rl/",
    "https://www.ipsecuritydepot.com/bosch-nde-8704-rl/nde-8704-rl/"
  ],
  "markets": [
    "EU",
    "global"
  ],
  "configs": {
    "frigate": {
      "detect": {
        "width": 3840,
        "height": 2160,
        "fps": 5
      },
      "rtsp_url_template": "rtsp://{user}:{pass}@{ip}:554/?inst=1",
      "best_substream": "rtsp://{user}:{pass}@{ip}:554/?inst=2",
      "recommended_stream_type": "go2rtc",
      "verified": false,
      "notes": "Bosch official RTSP scheme: /?inst=1 main, /?inst=2 sub (per Bosch 'RTSP usage with Bosch Video IP Devices'). Default admin user is 'service' (no factory default password — set one first). ONVIF Profile S/G (T/M on INTEOX). Not individually bench-tested."
    },
    "home_assistant": {
      "integration": "onvif",
      "connection_type": "local_push",
      "onvif_events": true,
      "notes": "Generic ONVIF integration; Bosch CPP cameras are ONVIF Profile S/G compliant. Use the 'service' account."
    },
    "blue_iris": {
      "profile": "ONVIF",
      "notes": "Bosch — use the ONVIF/RTSP (or 'Bosch') profile; default admin user is 'service'."
    }
  },
  "last_verified": "2026-07-06"
}
